cyvincenty.cpython-310-x86_64-linux-gnu.so
cyvincenty-1.0.7.dist-info/WHEEL
cyvincenty-1.0.7.dist-info/RECORD
cyvincenty-1.0.7.dist-info/METADATA
cyvincenty-1.0.7.dist-info/LICENSE
cyvincenty-1.0.7.dist-info/top_level.txt
