Metadata-Version: 2.1
Name: cyvincenty
Version: 1.0.7
Summary: Cython implementation of Vincenty distance.
Home-page: https://github.com/ipdata/cyvincenty
Author: Jonathan Kosgei
Author-email: jonathan@ipdata.co
Project-URL: Bug Tracker, https://github.com/ipdata/cyvincenty/issues
Classifier: Programming Language :: Python :: 3.9
Classifier: License :: OSI Approved :: MIT License
Classifier: Operating System :: OS Independent
Requires-Python: >=3
License-File: LICENSE
